{
  "id": "democracy-election",
  "title": "민주주의",
  "summary": "민주주의는 국민이 나라의 주인이라는 생각을 바탕으로 의견을 모으고 권리와 책임을 함께 지키는 제도와 생활 방식입니다.",
  "subjects": [
    "사회",
    "도덕",
    "국어"
  ],
  "topicTags": [
    "생활",
    "뉴스와 미디어"
  ],
  "aliases": [
    "민주주의와 선거",
    "민주주의",
    "국민 주권",
    "다수결",
    "권리와 책임",
    "시민 참여"
  ],
  "keywords": [
    "국민",
    "주권",
    "참여",
    "권리",
    "책임",
    "토론",
    "다수결",
    "소수 의견",
    "공공 문제"
  ],
  "related": [
    "election",
    "law-rules",
    "public-institution",
    "april-nineteen-revolution",
    "june-democratic-struggle",
    "nelson-mandela"
  ],
  "sources": [
    {
      "publisher": "중앙선거관리위원회",
      "title": "미래유권자 학습자료실",
      "url": "https://m.nec.go.kr/site/nec/ex/bbs/View.do?bcIdx=17593&cbIdx=1181",
      "usedFor": "민주시민 교육과 선거 참여의 기본 내용 확인",
      "license": "공식·공공 자료를 사실 확인용으로만 참고하고 학생용으로 새로 작성, 원문/이미지/표/그래프 복제 없음",
      "checkedAt": "2026-05-13"
    },
    {
      "publisher": "국가교육과정정보센터",
      "title": "2022 개정 교육과정 원문 및 교육과정 자료",
      "url": "https://www.ncic.re.kr/",
      "usedFor": "법과 규칙이 교과에서 다루어지는 내용 확인",
      "license": "공식·공공 자료를 사실 확인용으로만 참고하고 학생용으로 새로 작성, 원문/이미지/표/그래프 복제 없음",
      "checkedAt": "2026-05-14"
    },
    {
      "publisher": "헌법재판소 사이버 역사관",
      "title": "헌법 제·개정사",
      "url": "https://www.ccourt.go.kr/site/history/01/10102000000002020101203.jsp",
      "usedFor": "1948년 헌법 제정과 1987년 제9차 개정 헌법의 역사적 사실 확인",
      "license": "공식 자료를 사실 확인용으로만 참고하고 학생용으로 새로 작성, 원문/이미지/표/그래프 복제 없음",
      "checkedAt": "2026-05-27"
    }
  ],
  "copyrightNote": "이 지식은 공식 자료의 핵심 사실을 확인한 뒤 트루핑키스 위키가 학생용 문장으로 새로 작성했습니다. 원문 문단, 표, 이미지, 그래프를 복제하지 않았습니다.",
  "lastReviewed": "2026-05-20",
  "definition": "국민이 나라의 주인이라는 원칙에 따라 의견을 모으고 권리를 지키는 제도입니다.",
  "abstract": "민주주의는 국민 주권, 대표 선출, 권리 보장, 다수결과 소수 의견, 권력 견제를 중심으로 작동합니다.",
  "searchContexts": [
    "민주주의가 무엇인지 궁금할 때",
    "국민이 나라의 주인이라는 말이 무슨 뜻인지 알고 싶을 때",
    "다수결과 소수 의견 존중을 함께 생각할 때",
    "선거와 민주주의의 차이를 구분하고 싶을 때"
  ],
  "chapters": [
    {
      "title": "민주주의의 기본 원리",
      "sections": [
        {
          "heading": "국민 주권",
          "body": [
            "민주주의에서 국민 주권은 나라의 주인이 국민에게 있다는 원칙입니다.",
            "대한민국 헌법 제1조는 대한민국이 민주공화국이며, 주권이 국민에게 있고 모든 권력이 국민으로부터 나온다고 정합니다.",
            "나라의 일은 헌법과 법, 선거와 토론 같은 절차를 통해 정합니다.",
            "국민은 대표를 뽑고 공공 문제에 의견을 내며, 결정된 규칙 안에서 권리와 책임을 함께 가집니다."
          ]
        },
        {
          "heading": "권리와 책임",
          "body": [
            "민주주의는 개인의 자유와 권리를 보호하는 제도입니다.",
            "동시에 다른 사람의 권리를 침해하지 않고 공동체의 규칙을 지키는 책임도 포함합니다.",
            "표현의 자유, 참여, 법 앞의 평등은 민주주의를 설명할 때 자주 다루는 기본 요소입니다."
          ]
        }
      ]
    },
    {
      "title": "대표 선출과 의사 결정",
      "sections": [
        {
          "heading": "선거와 대표",
          "body": [
            "선거는 민주주의에서 대표를 뽑는 대표적인 방법입니다.",
            "대표는 시민의 의견을 대신 전달하고 공공 문제를 결정하는 역할을 맡습니다.",
            "선거 뒤에도 대표의 활동과 공약 이행은 시민의 관심과 감시를 받습니다."
          ]
        },
        {
          "heading": "다수결과 소수 의견",
          "body": [
            "다수결은 많은 사람이 찬성한 의견을 선택하는 결정 방법입니다.",
            "하지만 다수결은 소수 의견이나 기본권을 함부로 무시해도 된다는 뜻이 아닙니다.",
            "민주적 의사 결정에서는 토론, 타협, 절차의 공정성이 함께 다루어집니다."
          ]
        }
      ]
    },
    {
      "title": "민주주의를 유지하는 장치",
      "sections": [
        {
          "heading": "권력의 견제",
          "body": [
            "민주주의에서는 권력이 한 사람이나 한 기관에 지나치게 모이지 않도록 견제 장치를 둡니다.",
            "국회는 법률을 만들고, 행정부는 정책을 집행하며, 법원은 법에 따라 재판합니다.",
            "언론과 시민 참여는 권력 사용을 감시하고 공공 문제를 드러내는 역할을 합니다.",
            "권력 견제는 대표를 뽑은 뒤에도 민주주의가 계속 작동하게 하는 장치입니다."
          ]
        },
        {
          "heading": "사실에 근거한 공공 대화",
          "body": [
            "공공 문제를 논의할 때는 사실, 근거, 의견을 구분해야 합니다.",
            "소문과 허위 정보가 많아지면 시민이 공공 문제를 판단하기 어려워집니다.",
            "민주주의는 의견 차이를 없애는 제도가 아니라 절차 안에서 의견 차이를 다루는 제도입니다."
          ]
        }
      ]
    }
  ],
  "quiz": [
    {
      "question": "민주주의의 국민 주권에 대한 사실로 알맞은 것은 무엇인가요?",
      "choices": [
        "민주주의에서 국민 주권은 나라의 주인이 국민에게 있다는 원칙입니다.",
        "민주주의에서 국민 주권은 대표가 정한 일을 시민이 질문 없이 따르는 원칙입니다.",
        "민주주의에서 국민 주권은 국민이 대표를 뽑은 뒤에는 공공 문제에 의견을 낼 수 없다는 원칙입니다.",
        "민주주의에서 국민 주권은 다수 의견이 있으면 기본권을 제한해도 된다는 원칙입니다."
      ],
      "answerIndex": 0,
      "explanation": "국민 주권은 나라의 권력이 국민에게서 나온다는 민주주의의 기본 원리입니다.",
      "choiceExplanations": [
        "맞습니다. 국민 주권은 나라의 주인이 국민에게 있다는 원칙입니다.",
        "대표가 정한 일을 질문 없이 따르는 것은 국민 주권의 뜻과 맞지 않습니다.",
        "대표를 뽑은 뒤에도 시민은 청원, 토론, 시민 단체 활동, 언론 제보 등으로 공공 문제에 의견을 냅니다.",
        "다수 의견이 있어도 기본권은 함부로 제한할 수 없습니다."
      ]
    },
    {
      "question": "다수결에 대한 사실로 알맞은 것은 무엇인가요?",
      "choices": [
        "다수결은 많은 사람이 찬성한 의견을 선택하는 결정 방법입니다.",
        "다수결은 적은 사람이 낸 의견을 결정 과정에서 기록하지 않는 방법입니다.",
        "다수결은 토론 없이 가장 빠르게 말한 사람의 의견을 따르는 방식입니다.",
        "다수결은 많은 사람이 고른 의견이면 절차의 공정성과 기본권을 따로 살피지 않는 방식입니다."
      ],
      "answerIndex": 0,
      "explanation": "다수결은 민주적 결정 방법 중 하나이지만, 소수 의견과 기본권 보장도 함께 다루어집니다.",
      "choiceExplanations": [
        "맞습니다. 다수결은 많은 사람이 찬성한 의견을 선택하는 결정 방법입니다.",
        "다수결을 하더라도 소수 의견은 회의록, 반대 토론, 별도 의견으로 남습니다.",
        "가장 빠르게 말한 사람의 의견을 따르는 것은 다수결이 아닙니다.",
        "다수결도 절차의 공정성과 기본권 보장을 함께 고려해야 합니다."
      ]
    },
    {
      "question": "권력의 견제가 필요한 까닭으로 알맞은 것은 무엇인가요?",
      "choices": [
        "민주주의에서는 권력이 한 사람이나 한 기관에 지나치게 모이지 않도록 견제 장치를 둡니다.",
        "권력이 한곳에 모일수록 시민의 의견을 더 정확히 들을 수 있기 때문입니다.",
        "대표를 뽑으면 그 뒤에는 권력 사용을 살필 필요가 없어지기 때문입니다.",
        "권력 견제는 민주주의보다 왕정에서만 쓰이는 제도이기 때문입니다."
      ],
      "answerIndex": 0,
      "explanation": "권력 견제는 대표를 뽑은 뒤에도 권력이 법과 절차 안에서 쓰이도록 하는 장치입니다.",
      "choiceExplanations": [
        "맞습니다. 권력이 한 사람이나 한 기관에 지나치게 모이지 않도록 견제 장치를 둡니다.",
        "권력이 한곳에 모이면 시민의 다양한 의견이 제도에 반영되기 어렵습니다.",
        "대표를 뽑은 뒤에도 권력 사용을 살피는 장치가 작동합니다.",
        "권력 견제는 민주주의 제도에서 권력 남용을 줄이는 장치입니다."
      ]
    }
  ],
  "timeline": [
    {
      "date": "고대 그리스",
      "title": "아테네 민주 정치",
      "description": "아테네에서 시민이 정치에 참여하는 민주 정치의 모습이 나타났습니다."
    },
    {
      "date": "1948년",
      "title": "대한민국 헌법 제정",
      "description": "대한민국 헌법이 제정되고 민주공화국 원칙이 헌법에 담겼습니다."
    },
    {
      "date": "1987년",
      "title": "대통령 직선제 개헌",
      "description": "대통령 직선제 개헌으로 한국 민주주의 제도가 크게 바뀌었습니다."
    },
    {
      "date": "2020년대",
      "title": "민주 제도 운영",
      "description": "선거, 국회, 법원, 시민 참여를 통해 민주주의 제도가 운영됩니다."
    }
  ],
  "mainTopic": "사회와 생활",
  "subTopicPath": [
    "민주주의와 법"
  ],
  "categoryPaths": [
    [
      "사회와 생활",
      "민주주의와 법"
    ],
    [
      "뉴스와 미디어",
      "공공 문제 읽기"
    ]
  ]
}
