{
  "id": "animal-life-cycle",
  "title": "동물의 한살이",
  "summary": "동물의 한살이는 태어나고 자라며 어른 동물이 되어 번식하는 생명 과정입니다.",
  "definition": "동물의 한살이는 동물이 태어나 자라고 번식하는 전체 과정입니다.",
  "subjects": [
    "과학"
  ],
  "mainTopic": "과학",
  "subTopicPath": [
    "생명",
    "동물"
  ],
  "categoryPaths": [
    [
      "과학",
      "생명",
      "동물"
    ]
  ],
  "topicTags": [
    "동물과 식물",
    "환경"
  ],
  "aliases": [
    "한살이",
    "동물 성장",
    "변태",
    "알",
    "새끼"
  ],
  "keywords": [
    "알",
    "새끼",
    "애벌레",
    "번데기",
    "성체",
    "번식",
    "성장"
  ],
  "related": [
    "plant-life-cycle",
    "animal-classification",
    "habitat-adaptation",
    "biodiversity"
  ],
  "sources": [
    {
      "publisher": "국립생태원",
      "title": "생태교육 자료",
      "url": "https://www.nie.re.kr/",
      "usedFor": "동물의 성장과 한살이, 변태 과정의 기본 내용 확인",
      "license": "공식·공공 자료를 사실 확인용으로 참고하고 학생용으로 새로 작성, 원문/이미지/표/그래프 복제 없음",
      "checkedAt": "2026-05-20"
    },
    {
      "publisher": "국가교육과정정보센터",
      "title": "2022 개정 교육과정 원문 및 교육과정 자료",
      "url": "https://www.ncic.re.kr/",
      "usedFor": "동물의 한살이를 관찰하고 생명 과정으로 설명하는 범위 확인",
      "license": "공식·공공 자료를 사실 확인용으로 참고하고 학생용으로 새로 작성, 원문/이미지/표/그래프 복제 없음",
      "checkedAt": "2026-05-20"
    }
  ],
  "searchContexts": [
    "동물의 한살이를 알고 싶을 때",
    "동물의 한살이를 생활 속 현상과 연결할 때",
    "동물의 한살이를 다른 개념과 구분할 때"
  ],
  "abstract": "동물의 한살이는 태어나고 자라며 어른 동물이 되어 번식하는 생명 과정입니다.",
  "chapters": [
    {
      "title": "동물이 태어나고 자라는 과정",
      "sections": [
        {
          "heading": "한살이의 흐름",
          "body": [
            "동물은 종류에 따라 알에서 나오거나 어미 몸에서 새끼로 태어납니다.",
            "태어난 뒤 자라고 어른 동물이 되어 번식하면 새로운 세대가 이어집니다."
          ]
        },
        {
          "heading": "알에서 나오는 동물",
          "body": [
            "새, 물고기, 곤충, 개구리처럼 알에서 새끼가 나오는 동물이 있습니다.",
            "나비는 알, 애벌레, 번데기, 어른벌레 단계를 거치며 모습이 크게 달라집니다."
          ]
        }
      ]
    },
    {
      "title": "동물마다 다른 자람",
      "sections": [
        {
          "heading": "변태와 성장",
          "body": [
            "개구리는 올챙이에서 다리가 생기고 꼬리가 줄어들며 어른 개구리로 자랍니다.",
            "병아리가 닭이 되는 과정처럼 기본 모습은 비슷하지만 크기와 기능이 달라지는 경우가 있습니다."
          ]
        },
        {
          "heading": "사는 곳과 먹이 조건",
          "body": [
            "동물의 한살이는 사는 곳과 먹이 조건의 영향을 받습니다.",
            "물속에서 자라는 시기와 땅에서 사는 시기가 나뉘는 동물은 각각 필요한 환경이 다릅니다."
          ]
        }
      ]
    },
    {
      "title": "생명이 다음 세대로 이어짐",
      "sections": [
        {
          "heading": "번식과 새로운 세대",
          "body": [
            "한살이는 한 동물의 성장만이 아니라 생명이 다음 세대로 이어지는 과정을 보여 줍니다.",
            "어른 동물이 번식하면 새로운 세대가 시작됩니다."
          ]
        },
        {
          "heading": "새끼로 태어나는 동물",
          "body": [
            "개, 고양이, 사람처럼 어미 몸에서 자라 새끼로 태어나는 동물이 있습니다.",
            "많은 동물은 자라면서 몸집이 커지고 몸의 기능이 발달합니다."
          ]
        }
      ]
    }
  ],
  "quiz": [
    {
      "question": "동물의 한살이를 설명하는 문장으로 알맞은 것은 무엇인가요?",
      "choices": [
        "나비는 알, 애벌레, 번데기, 어른벌레 단계를 거치며 모습이 크게 달라집니다.",
        "나비는 어른벌레가 된 뒤 알과 애벌레 단계를 거치며 모습이 작아집니다.",
        "나비는 알에서 바로 어른벌레가 되어 번데기 단계를 거치지 않습니다.",
        "나비의 한살이는 씨, 싹, 꽃, 열매의 순서로만 진행됩니다."
      ],
      "answerIndex": 0,
      "explanation": "동물의 한살이는 조건과 과정이 함께 작용하는 과학 개념입니다."
    },
    {
      "question": "동물의 한살이가 보여 주는 생명 과정은 무엇인가요?",
      "choices": [
        "한살이는 한 동물의 성장만이 아니라 생명이 다음 세대로 이어지는 과정을 보여 줍니다.",
        "한살이는 한 동물이 이동한 거리와 빠르기만 나타내는 기록입니다.",
        "한살이는 어른 동물이 된 뒤에만 시작되므로 알이나 새끼 단계는 포함하지 않습니다.",
        "한살이는 동물의 먹이 종류만 비교하는 방법이어서 성장과 번식 단계는 다루지 않습니다."
      ],
      "answerIndex": 0,
      "explanation": "동물의 한살이는 태어남, 성장, 어른 동물, 번식으로 이어지는 생명 과정입니다. 한 개체의 변화뿐 아니라 다음 세대로 이어지는 흐름을 함께 보여 줍니다."
    }
  ],
  "lastReviewed": "2026-05-20",
  "copyrightNote": "이 지식은 공식 자료의 핵심 사실을 확인한 뒤 트루핑키스 위키가 학생용 문장과 구조로 새로 작성했습니다. 원문 문단, 표, 이미지, 그래프를 복제하지 않았습니다."
}
