{
  "id": "light-properties",
  "title": "빛의 성질",
  "summary": "빛의 성질은 빛이 곧게 나아가고, 물체에 부딪히거나 다른 물질을 지날 때 반사·굴절·흡수·통과가 일어나는 특징입니다.",
  "definition": "빛의 성질은 빛이 나아가고 물체와 만날 때 나타나는 여러 특징입니다.",
  "subjects": [
    "과학"
  ],
  "mainTopic": "과학",
  "subTopicPath": [
    "운동과 에너지",
    "빛"
  ],
  "categoryPaths": [
    [
      "과학",
      "운동과 에너지",
      "빛"
    ]
  ],
  "topicTags": [
    "과학기술",
    "생활"
  ],
  "aliases": [
    "빛",
    "직진",
    "반사",
    "굴절",
    "그림자",
    "렌즈"
  ],
  "keywords": [
    "빛의 직진",
    "반사",
    "굴절",
    "흡수",
    "통과",
    "그림자",
    "거울"
  ],
  "related": [
    "light-shadow",
    "light-reflection",
    "light-refraction-lens",
    "energy"
  ],
  "sources": [
    {
      "publisher": "사이언스올",
      "title": "과학백과사전",
      "url": "https://www.scienceall.com/",
      "usedFor": "빛의 직진, 반사, 굴절, 그림자의 기본 개념 확인",
      "license": "공식·공공 자료를 사실 확인용으로 참고하고 학생용으로 새로 작성, 원문/이미지/표/그래프 복제 없음",
      "checkedAt": "2026-05-21"
    },
    {
      "publisher": "국가교육과정정보센터",
      "title": "2022 개정 교육과정 원문 및 교육과정 자료",
      "url": "https://www.ncic.re.kr/",
      "usedFor": "초등 과학 내용 영역과 학생용 설명 범위 확인",
      "license": "공식·공공 자료를 사실 확인용으로 참고하고 학생용으로 새로 작성, 원문/이미지/표/그래프 복제 없음",
      "checkedAt": "2026-05-21"
    }
  ],
  "searchContexts": [
    "빛이 어떻게 나아가는지 찾을 때",
    "그림자가 생기는 까닭이 궁금할 때",
    "거울과 렌즈의 원리를 비교할 때"
  ],
  "abstract": "빛의 성질은 우리 눈에 물체가 보이는 까닭과 거울, 렌즈, 그림자가 생기는 원리를 설명합니다.",
  "chapters": [
    {
      "title": "빛의 성질의 뜻과 범위",
      "sections": [
        {
          "heading": "기본 뜻",
          "body": [
            "빛의 성질은 빛이 나아가고 물체와 만날 때 나타나는 여러 특징입니다.",
            "빛은 같은 물질 속에서 대체로 곧게 나아갑니다.",
            "빛은 물체를 만나면 반사되거나 흡수되거나 통과할 수 있고, 다른 물질로 들어갈 때 굴절될 수 있습니다."
          ]
        },
        {
          "heading": "구분하는 말",
          "body": [
            "반사는 빛이 되돌아 나오는 현상이고, 굴절은 빛이 다른 물질로 들어가며 방향이 꺾이는 현상입니다.",
            "투명한 유리는 빛을 잘 통과시키지만, 불투명한 물체는 빛을 막아 그림자를 만들 수 있습니다."
          ]
        }
      ]
    },
    {
      "title": "빛의 성질에서 일어나는 변화",
      "sections": [
        {
          "heading": "일어나는 과정",
          "body": [
            "빛이 눈에 들어오면 우리는 물체의 모양과 색을 볼 수 있습니다.",
            "물체의 표면과 물질의 성질이 다르기 때문에 빛이 반사되거나 흡수되는 정도가 달라집니다."
          ]
        },
        {
          "heading": "관찰되는 모습",
          "body": [
            "손전등 빛을 거울에 비추면 빛이 다른 방향으로 되돌아가는 모습을 관찰할 수 있습니다.",
            "돋보기는 빛이 렌즈를 지날 때 굴절되는 성질을 이용합니다."
          ]
        }
      ]
    },
    {
      "title": "빛의 성질의 쓰임과 연결",
      "sections": [
        {
          "heading": "다른 개념과의 관계",
          "body": [
            "빛의 성질은 그림자, 빛의 반사, 빛의 굴절과 렌즈를 묶어 설명하는 기본 개념입니다.",
            "강한 빛이나 레이저를 눈에 직접 비추면 눈을 다칠 수 있습니다."
          ]
        },
        {
          "heading": "정리할 내용",
          "body": [
            "빛의 성질을 알면 거울, 렌즈, 그림자, 색이 보이는 현상을 설명할 수 있습니다.",
            "빛의 방향과 물체의 위치를 바꾸어 보면 그림자의 크기와 방향이 달라집니다."
          ]
        }
      ]
    }
  ],
  "quiz": [
    {
      "question": "빛의 성질의 기본 뜻으로 알맞은 것은 무엇인가요?",
      "choices": [
        "빛은 같은 물질 속에서 대체로 곧게 나아갑니다.",
        "빛은 공기 속에서만 소리로 바뀌는 물질입니다.",
        "빛은 물체에 닿아도 방향이나 세기가 변하지 않는 먼지입니다.",
        "빛은 생물이 먹이를 얻는 순서만 나타내는 말입니다."
      ],
      "answerIndex": 0,
      "explanation": "빛은 나아가고 물체와 만날 때 여러 성질을 보입니다."
    },
    {
      "question": "빛의 성질를 관찰하거나 적용한 설명으로 알맞은 것은 무엇인가요?",
      "choices": [
        "빛의 성질을 알면 거울, 렌즈, 그림자, 색이 보이는 현상을 설명할 수 있습니다.",
        "거울과 렌즈는 빛의 반사나 굴절보다 물체의 무게를 바꾸는 도구입니다.",
        "그림자는 물체가 소리를 흡수할 때만 생기는 흔적입니다.",
        "반사와 굴절은 먹이사슬의 단계 이름입니다."
      ],
      "answerIndex": 0,
      "explanation": "빛의 성질은 여러 광학 현상을 설명합니다."
    }
  ],
  "lastReviewed": "2026-05-21",
  "copyrightNote": "이 지식은 공식 자료의 핵심 사실을 확인한 뒤 트루핑키스 위키가 학생용 문장과 구조로 새로 작성했습니다. 원문 문단, 표, 이미지, 그래프를 복제하지 않았습니다."
}
