{
  "id": "light-shadow",
  "title": "빛과 그림자",
  "summary": "그림자는 빛이 물체에 막혀 뒤쪽에 어두운 부분이 생기는 현상입니다.",
  "subjects": [
    "과학",
    "미술"
  ],
  "topicTags": [
    "생활",
    "창작"
  ],
  "aliases": [
    "그림자",
    "빛의 방향",
    "빛의 직진",
    "투명한 물체"
  ],
  "keywords": [
    "빛",
    "그림자",
    "방향",
    "거리",
    "크기",
    "스크린",
    "관찰"
  ],
  "related": [
    "light-properties",
    "solar-altitude-noon",
    "energy"
  ],
  "sources": [
    {
      "publisher": "한국과학창의재단 사이언스올",
      "title": "생활과학: 빛과 그림자 관련 자료",
      "url": "https://www.scienceall.com/brd/board/510/L/menu/289?bbsSn=45454&brdType=R",
      "license": "공개 자료를 사실 확인용으로만 참고하고 학생용으로 새로 작성, 원문/이미지/표/그래프 복제 없음",
      "checkedAt": "2026-05-14",
      "usedFor": "빛과 그림자의 과학 개념과 교과 연결 내용 확인"
    },
    {
      "publisher": "국가교육과정정보센터",
      "title": "2022 개정 교육과정 원문 및 교육과정 자료",
      "url": "https://www.ncic.re.kr/",
      "license": "공식·공공 자료를 사실 확인용으로만 참고하고 학생용으로 새로 작성, 원문/이미지/표/그래프 복제 없음",
      "checkedAt": "2026-05-14",
      "usedFor": "빛과 그림자와 연결되는 교과 내용 확인"
    }
  ],
  "copyrightNote": "이 지식은 공식 자료의 핵심 사실을 확인한 뒤 트루핑키스 위키가 학생용 문장으로 새로 작성했습니다. 원문 문단, 표, 이미지, 그래프를 복제하지 않았습니다.",
  "lastReviewed": "2026-05-14",
  "definition": "빛이 물체에 막혀 뒤쪽에 어두운 부분이 생기는 현상입니다.",
  "abstract": "빛과 그림자는 빛이 곧게 나아가다가 물체에 막힐 때 생기는 어두운 부분과 그 크기·방향의 변화를 설명합니다.",
  "searchContexts": [
    "그림자가 궁금할 때",
    "빛의 방향이 궁금할 때",
    "빛의 직진이 궁금할 때",
    "투명한 물체가 궁금할 때",
    "빛과 물체 때문에 그림자가 생기는 까닭을 찾을 때"
  ],
  "chapters": [
    {
      "title": "그림자의 생성 원리",
      "sections": [
        {
          "heading": "빛이 물체에 막힐 때",
          "body": [
            "빛이 물체에 막히면 빛이 닿지 않는 쪽에 그림자가 생깁니다.",
            "빛은 보통 곧게 나아가기 때문에 물체가 빛의 길을 가리면 그 뒤쪽에 어두운 모양이 나타납니다.",
            "그림자는 빛, 물체, 그림자가 비치는 면이 있을 때 뚜렷하게 관찰됩니다."
          ]
        },
        {
          "heading": "물체가 빛을 통과시키는 정도",
          "body": [
            "투명한 물체, 반투명한 물체, 불투명한 물체는 빛을 통과시키는 정도가 다릅니다.",
            "유리처럼 빛을 잘 통과시키는 물체는 그림자가 흐리거나 잘 보이지 않을 수 있습니다.",
            "두꺼운 종이나 책처럼 빛을 잘 막는 물체는 비교적 뚜렷한 그림자를 만들 수 있습니다."
          ]
        }
      ]
    },
    {
      "title": "그림자의 크기와 방향",
      "sections": [
        {
          "heading": "빛의 위치와 거리",
          "body": [
            "빛의 위치, 물체와 화면 사이의 거리가 달라지면 그림자의 크기와 방향도 달라질 수 있습니다.",
            "손전등을 물체에 가까이 대거나 멀리 두면 그림자의 크기가 달라지는 모습을 관찰할 수 있습니다.",
            "해의 위치가 달라지면 나무나 건물 옆에 생기는 그림자의 방향과 길이도 달라집니다.",
            "빛이 물체에 가까울수록 그림자가 커지고, 빛이 물체에서 멀어질수록 그림자가 작아지는 경우가 많습니다."
          ]
        },
        {
          "heading": "그림자 관찰 조건",
          "body": [
            "햇빛이나 강한 불빛을 직접 오래 바라보면 눈에 해로울 수 있습니다.",
            "그림자의 크기와 방향은 빛의 위치, 물체의 위치, 화면의 위치와 관련됩니다.",
            "같은 물체라도 빛이 오는 방향이 달라지면 그림자가 생기는 위치가 달라집니다."
          ]
        }
      ]
    },
    {
      "title": "생활 속 그림자",
      "sections": [
        {
          "heading": "해의 위치와 그림자",
          "body": [
            "해가 동쪽에서 떠서 남쪽 하늘을 지나 서쪽으로 이동해 보이면 그림자의 방향도 함께 달라집니다.",
            "해시계는 해의 위치에 따라 달라지는 그림자를 이용해 시간을 나타내는 장치입니다."
          ]
        },
        {
          "heading": "그림자와 표현",
          "body": [
            "그림자극은 빛과 막, 물체의 그림자를 이용해 이야기를 표현하는 공연입니다.",
            "미술에서는 빛과 그림자의 차이를 이용해 물체의 입체감과 공간감을 나타냅니다."
          ]
        }
      ]
    }
  ],
  "quiz": [
    {
      "question": "그림자가 생기는 까닭으로 알맞은 것은 무엇인가요?",
      "choices": [
        "빛이 물체에 막히면 빛이 닿지 않는 쪽에 그림자가 생깁니다.",
        "투명한 유리를 통과한 빛은 진한 검은 그림자를 만듭니다.",
        "물체가 없어도 빛만 있으면 바닥에는 물체 모양의 그림자가 생깁니다.",
        "그림자는 물체가 빛을 받아 뒤쪽으로 밀려날 때 생기는 자국입니다."
      ],
      "answerIndex": 0,
      "explanation": "그림자는 빛의 길이 물체에 의해 가려질 때 생기는 현상입니다.",
      "choiceExplanations": [
        "맞습니다. 빛이 물체에 막히면 빛이 닿지 않는 쪽에 그림자가 생깁니다.",
        "투명한 유리는 빛을 잘 통과시키므로 진한 검은 그림자를 만들기 어렵습니다.",
        "그림자는 빛과 물체가 함께 있어야 물체 모양으로 생길 수 있습니다.",
        "그림자는 물체가 밀려난 자국이 아니라 빛이 가려져 생기는 어두운 부분입니다."
      ]
    },
    {
      "question": "물체와 빛의 관계를 설명한 문장으로 맞는 것은 무엇인가요?",
      "choices": [
        "투명한 물체, 반투명한 물체, 불투명한 물체는 빛을 통과시키는 정도가 다릅니다.",
        "투명한 물체와 불투명한 물체는 빛을 통과시키는 정도가 같습니다.",
        "불투명한 물체는 빛을 더 잘 통과시키기 때문에 그림자가 더 흐려집니다.",
        "반투명한 물체는 빛과 관련이 없고 물체의 무게에 따라 그림자가 결정됩니다."
      ],
      "answerIndex": 0,
      "explanation": "빛이 얼마나 통과하느냐에 따라 그림자의 뚜렷함도 달라질 수 있습니다.",
      "choiceExplanations": [
        "맞습니다. 물체가 빛을 통과시키는 정도에 따라 그림자의 진하기가 달라질 수 있습니다.",
        "투명한 물체와 불투명한 물체는 빛을 통과시키는 정도가 다릅니다.",
        "불투명한 물체는 빛을 잘 막기 때문에 비교적 뚜렷한 그림자를 만들 수 있습니다.",
        "그림자는 물체의 무게가 아니라 빛의 통과 정도와 위치 관계에 영향을 받습니다."
      ]
    },
    {
      "question": "그림자의 크기와 방향이 달라지는 까닭으로 알맞은 것은 무엇인가요?",
      "choices": [
        "빛의 위치, 물체와 화면 사이의 거리가 달라지면 그림자의 크기와 방향도 달라질 수 있습니다.",
        "그림자의 크기와 방향은 물체의 색으로만 정해지고 빛의 위치는 영향을 주지 않습니다.",
        "그림자는 처음 생긴 크기와 방향을 유지해서 빛이나 화면의 위치를 바꾸어도 달라지지 않습니다.",
        "화면을 물체에 가까이 하거나 멀리 해도 그림자의 크기는 물체의 실제 크기와 같게만 나타납니다."
      ],
      "answerIndex": 0,
      "explanation": "그림자는 빛이 물체에 막힐 때 생기므로 빛, 물체, 화면의 위치에 따라 모양과 크기가 달라집니다.",
      "choiceExplanations": [
        "맞습니다. 빛과 물체, 화면의 위치가 달라지면 그림자의 크기와 방향도 달라질 수 있습니다.",
        "그림자의 크기와 방향은 물체의 색만으로 정해지지 않습니다.",
        "빛이나 화면의 위치가 달라지면 그림자의 크기와 방향도 달라질 수 있습니다.",
        "화면과 물체 사이의 거리가 달라지면 그림자의 크기도 달라질 수 있습니다."
      ]
    }
  ],
  "mainTopic": "과학",
  "subTopicPath": [
    "물질과 에너지"
  ],
  "categoryPaths": [
    [
      "과학",
      "물질과 에너지"
    ],
    [
      "문화와 표현",
      "미술과 표현"
    ]
  ]
}
